APPNAME
VERSION
requirements.txt
bikaclient/__init__.py
bikaclient/__version__.py
bikaclient-0.5.6.dist-info/METADATA
bikaclient-0.5.6.dist-info/WHEEL
bikaclient-0.5.6.dist-info/top_level.txt
bikaclient-0.5.6.dist-info/zip-safe
bikaclient-0.5.6.dist-info/RECORD
