Metadata-Version: 2.1
Name: bikaclient
Version: 0.5.6
Summary: client package for bika lims
Home-page: https://github.com/ratzeni/bika.client
Author: Atzeni Rossano,Gianmauro Cuccuru
Author-email: <ratzeni@crs4.it>,<gmauro@crs4.it>
License: MIT
Keywords: utilities
Platform: Posix; MacOS X; Windows
Classifier: Development Status :: 3 - Alpha
Classifier: Intended Audience :: Developers
Classifier: License :: OSI Approved :: MIT License
Classifier: Operating System :: OS Independent
Classifier: Topic :: Internet 
Classifier: Programming Language :: Python :: 2.7
Classifier: Programming Language :: Python :: 3.5
Classifier: Programming Language :: Python :: 3.6
Requires-Dist: six
Requires-Dist: keyring
Requires-Dist: keyrings.alt
